./.gitignore
./PKG-INFO
./README.md
./dice_roller.py
./pyproject.toml
./server.py
iflow_mcp_ai_maker_space_aim_mcp_demo-0.1.0.dist-info/METADATA
iflow_mcp_ai_maker_space_aim_mcp_demo-0.1.0.dist-info/WHEEL
iflow_mcp_ai_maker_space_aim_mcp_demo-0.1.0.dist-info/entry_points.txt
iflow_mcp_ai_maker_space_aim_mcp_demo-0.1.0.dist-info/RECORD
