Metadata-Version: 2.4
Name: iflow-mcp_ai-maker-space_aim_mcp_demo
Version: 0.1.0
Summary: Add your description here
Requires-Python: >=3.13
Requires-Dist: langgraph>=0.3.27
Requires-Dist: mcp[cli]>=1.6.0
Requires-Dist: numpy>=2.2.4
Requires-Dist: openai>=1.72.0
Requires-Dist: python-dotenv>=1.1.0
Requires-Dist: tavily-python>=0.5.4
